ziginstall/__init__.py
ziginstall/_locations.py
ziginstall/_logging.py
ziginstall/cli.py
ziginstall/install/__init__.py
ziginstall/install/_core.py
ziginstall/install/_install_steps.py
ziginstall/install/_verification.py
ziginstall/install/cli.py
ziginstall/version_management/__init__.py
ziginstall/version_management/cli.py
ziginstall/version_management/core.py
ziginstall-0.1.4.dist-info/LICENSE
ziginstall-0.1.4.dist-info/METADATA
ziginstall-0.1.4.dist-info/WHEEL
ziginstall-0.1.4.dist-info/entry_points.txt
ziginstall-0.1.4.dist-info/RECORD
