Metadata-Version: 2.1
Name: ziginstall
Version: 0.1.4
Summary: A simple CLI to install the Zig programming language on your system and manage versions.
License: MIT
Keywords: zig,install,cli,ziglang
Author: charlotdupont
Author-email: charlo.dupont@gmail.com
Requires-Python: >=3.12,<4.0
Classifier: Intended Audience :: Developers
Classifier: License :: OSI Approved :: MIT License
Classifier: Programming Language :: Python :: 3
Classifier: Programming Language :: Python :: 3.12
Classifier: Topic :: Software Development
Classifier: Topic :: System :: Installation/Setup
Classifier: Topic :: System :: Software Distribution
Classifier: Topic :: Utilities
Requires-Dist: click (>=8.1.7,<9.0.0)
Requires-Dist: colorama (>=0.4.6,<0.5.0)
Requires-Dist: packaging (>=24.0,<25.0)
Requires-Dist: platformdirs (>=4.2.2,<5.0.0)
Requires-Dist: requests (>=2.32.3,<3.0.0)
Requires-Dist: rich (>=13.7.1,<14.0.0)
